airwater/__init__.py
airwater/_version.py
airwater/jsonsaveoper.py
airwater-1.0.3.dist-info/DESCRIPTION.rst
airwater-1.0.3.dist-info/METADATA
airwater-1.0.3.dist-info/RECORD
airwater-1.0.3.dist-info/WHEEL
airwater-1.0.3.dist-info/metadata.json
airwater-1.0.3.dist-info/top_level.txt
