Metadata-Version: 2.0
Name: airwater
Version: 1.0.3
Summary: Better Tools Library For Write Spider With Python
Home-page: https://airwater.readthedocs.io
Author: Airwater
Author-email: airwater@gmail.com
License: Apache 2.0
Project-URL: Repository, https://github.com/airwa/airwater
Project-URL: Bug Reports, https://github.com/airwa/airwater/issues
Project-URL: Documentation, https://airwater.readthedocs.io
Keywords: airwater spider library tools
Platform: UNKNOWN
Classifier: Development Status :: 4 - Beta
Classifier: Intended Audience :: Developers
Classifier: License :: OSI Approved :: Apache Software License
Classifier: Topic :: Software Development :: Libraries :: Python Modules
Classifier: Programming Language :: Python :: 2
Classifier: Programming Language :: Python :: 2.7
Classifier: Programming Language :: Python :: 3
Classifier: Programming Language :: Python :: 3.5
Classifier: Programming Language :: Python :: 3.6
Classifier: Programming Language :: Python :: 3.7
Classifier: Programming Language :: Python :: 3.8
Requires-Python: >=2.7, !=3.0.*, !=3.1.*, !=3.2.*, !=3.3.*, !=3.4.*
Requires-Dist: arrow (>=0.14.6)
Requires-Dist: python-dateutil
